__init__.py
colors.py
exemple.py
mytui.py
window.py
MyTUI-1.0.9.dist-info/LICENSE
MyTUI-1.0.9.dist-info/METADATA
MyTUI-1.0.9.dist-info/WHEEL
MyTUI-1.0.9.dist-info/top_level.txt
MyTUI-1.0.9.dist-info/RECORD
