Metadata-Version: 2.1
Name: MyTUI
Version: 1.0.9
Summary: Easily create terminal user interface containing menus, text boxes and input fields for your projects
Author: Paulin-Dev
Project-URL: Homepage, https://github.com/Paulin-Dev/TUI
Classifier: Programming Language :: Python :: 3
Classifier: License :: OSI Approved :: MIT License
Classifier: Operating System :: OS Independent
Requires-Python: >=3.5
License-File: LICENSE
Requires-Dist: getkey
